speednet/__init__.py
speednet/eval_criterion/__init__.py
speednet/eval_criterion/conv_vae_loss.py
speednet/vae/ConvVae.py
speednet/vae/__init__.py
speednet/vae/utils.py
speednet-0.0.0.dist-info/LICENSE
speednet-0.0.0.dist-info/METADATA
speednet-0.0.0.dist-info/WHEEL
speednet-0.0.0.dist-info/top_level.txt
speednet-0.0.0.dist-info/RECORD
