Metadata-Version: 2.1
Name: speednet
Version: 0.0.0
Summary: This is a package that aims to make various neural networks accessbile to a wider audience by providing black box models.
Home-page: https://github.com/Abhranta/speednet
Author: Abhranta Panigrahi
Author-email: abhranta.panigrahir@example.com
License: UNKNOWN
Platform: UNKNOWN
Classifier: Programming Language :: Python :: 3
Classifier: License :: OSI Approved :: MIT License
Classifier: Operating System :: OS Independent
Requires-Python: >=3.6
Requires-Dist: torch (>=1.6.0)
